ansys/chemkin/core/__init__.py
ansys/chemkin/core/chemistry.py
ansys/chemkin/core/chemkin_wrapper.py
ansys/chemkin/core/color.py
ansys/chemkin/core/constants.py
ansys/chemkin/core/flame.py
ansys/chemkin/core/grid.py
ansys/chemkin/core/hybridreactornetwork.py
ansys/chemkin/core/info.py
ansys/chemkin/core/inlet.py
ansys/chemkin/core/logger.py
ansys/chemkin/core/mixture.py
ansys/chemkin/core/reactormodel.py
ansys/chemkin/core/realgaseos.py
ansys/chemkin/core/steadystatesolver.py
ansys/chemkin/core/utilities.py
ansys/chemkin/core/batchreactors/batchreactor.py
ansys/chemkin/core/data/ChemkinKeywordTips.yaml
ansys/chemkin/core/engines/HCCI.py
ansys/chemkin/core/engines/SI.py
ansys/chemkin/core/engines/engine.py
ansys/chemkin/core/flowreactors/PFR.py
ansys/chemkin/core/premixedflames/premixedflame.py
ansys/chemkin/core/stirreactors/PSR.py
ansys/chemkin/core/stirreactors/openreactor.py
ansys_chemkin_core-0.1.1.dist-info/licenses/LICENSE
ansys_chemkin_core-0.1.1.dist-info/WHEEL
ansys_chemkin_core-0.1.1.dist-info/METADATA
ansys_chemkin_core-0.1.1.dist-info/RECORD
