Metadata-Version: 2.4
Name: ansys-chemkin-core
Version: 0.1.1
Summary: PyChemkin provides Pythonic interface to Ansys Chemkin utilities and reactor models
Author-email: "ANSYS, Inc." <pyansys.core@ansys.com>
Maintainer-email: "ANSYS, Inc." <pyansys.core@ansys.com>
Requires-Python: >=3.10,<4
Classifier: Development Status :: 4 - Beta
Classifier: Intended Audience :: Science/Research
Classifier: Programming Language :: Python :: 3
Classifier: License :: OSI Approved :: MIT License
Classifier: Operating System :: Microsoft :: Windows :: Windows 11
Classifier: Operating System :: Microsoft :: Windows :: Windows 10
Classifier: Natural Language :: English
License-File: LICENSE
Requires-Dist: matplotlib>=3.10.8
Requires-Dist: numpy>=1.14.0,<3.0.0
Requires-Dist: pyyaml>=6.0
Project-URL: Discussions, https://github.com/ansys/pychemkin/discussions
Project-URL: Documentation, https://chemkin.docs.pyansys.com/
Project-URL: Issues, https://github.com/ansys/pychemkin/issues
Project-URL: Releases, https://github.com/ansys/pychemkin/releases/
Project-URL: Source, https://github.com/ansys/pychemkin
